teenagi/__init__.py
teenagi/cli.py
teenagi/core.py
teenagi-0.5.0.dist-info/LICENSE
teenagi-0.5.0.dist-info/METADATA
teenagi-0.5.0.dist-info/WHEEL
teenagi-0.5.0.dist-info/entry_points.txt
teenagi-0.5.0.dist-info/RECORD
