Metadata-Version: 2.1
Name: teenagi
Version: 0.5.0
Summary: A Python package for building AI agents capable of making multiple function calls in sequence
Home-page: https://github.com/jordan/teen-agi
License: MIT
Keywords: ai,agi
Author: Jordan Plows
Author-email: jordan@plows.ai
Requires-Python: >=3.11,<4.0
Classifier: Development Status :: 4 - Beta
Classifier: Intended Audience :: Developers
Classifier: License :: OSI Approved :: MIT License
Classifier: Programming Language :: Python :: 3
Classifier: Programming Language :: Python :: 3.11
Classifier: Programming Language :: Python :: 3.12
Requires-Dist: anthropic (>=0.7.0,<0.8.0)
Requires-Dist: flask (>=2.3.0,<3.0.0)
Requires-Dist: flask-wtf (>=1.1.1,<2.0.0)
Requires-Dist: openai (>=1.1.0,<2.0.0)
Requires-Dist: plotly (>=5.15.0,<6.0.0)
Requires-Dist: python-dotenv (>=1.0.0,<2.0.0)
Project-URL: Bug Tracker, https://github.com/jordan/teen-agi/issues
Project-URL: Repository, https://github.com/jordan/teen-agi
